tripwire/__init__.py
tripwire/_core_legacy.py
tripwire/branding.py
tripwire/config.py
tripwire/constants.py
tripwire/exceptions.py
tripwire/git_audit.py
tripwire/parser.py
tripwire/scanner.py
tripwire/schema.py
tripwire/schema_diff.py
tripwire/secrets.py
tripwire/tool_config.py
tripwire/validation.py
tripwire/analysis/__init__.py
tripwire/analysis/dependency_graph.py
tripwire/analysis/models.py
tripwire/analysis/usage_tracker.py
tripwire/cli/__init__.py
tripwire/cli/__main__.py
tripwire/cli/progress.py
tripwire/cli/commands/__init__.py
tripwire/cli/commands/analyze.py
tripwire/cli/commands/check.py
tripwire/cli/commands/diff.py
tripwire/cli/commands/docs.py
tripwire/cli/commands/generate.py
tripwire/cli/commands/init.py
tripwire/cli/commands/install_hooks.py
tripwire/cli/commands/schema.py
tripwire/cli/commands/sync.py
tripwire/cli/commands/validate.py
tripwire/cli/commands/plugin/__init__.py
tripwire/cli/commands/plugin/install.py
tripwire/cli/commands/plugin/ls.py
tripwire/cli/commands/plugin/remove.py
tripwire/cli/commands/plugin/search.py
tripwire/cli/commands/plugin/update.py
tripwire/cli/commands/security/__init__.py
tripwire/cli/commands/security/audit.py
tripwire/cli/commands/security/scan.py
tripwire/cli/formatters/__init__.py
tripwire/cli/formatters/analyze.py
tripwire/cli/formatters/audit.py
tripwire/cli/formatters/docs.py
tripwire/cli/templates/__init__.py
tripwire/cli/utils/__init__.py
tripwire/cli/utils/console.py
tripwire/cli/utils/helpers.py
tripwire/config/__init__.py
tripwire/config/models.py
tripwire/config/repository.py
tripwire/config/source.py
tripwire/config/sources/__init__.py
tripwire/config/sources/env_file.py
tripwire/config/sources/toml_source.py
tripwire/core/__init__.py
tripwire/core/inference.py
tripwire/core/loader.py
tripwire/core/plugin_system.py
tripwire/core/registry.py
tripwire/core/tripwire_v2.py
tripwire/core/validation_orchestrator.py
tripwire/plugins/__init__.py
tripwire/plugins/base.py
tripwire/plugins/errors.py
tripwire_py-0.13.1.dist-info/METADATA
tripwire_py-0.13.1.dist-info/WHEEL
tripwire_py-0.13.1.dist-info/entry_points.txt
tripwire_py-0.13.1.dist-info/licenses/LICENSE
tripwire_py-0.13.1.dist-info/RECORD
