Metadata-Version: 2.4
Name: tripwire-py
Version: 0.13.1
Summary: Catch config errors before they explode - Python environment variable management with import-time validation, type safety, and secret detection
Project-URL: Homepage, https://github.com/Daily-Nerd/TripWire
Project-URL: Documentation, https://github.com/Daily-Nerd/TripWire/tree/main/docs
Project-URL: Repository, https://github.com/Daily-Nerd/TripWire
Project-URL: Issues, https://github.com/Daily-Nerd/TripWire/issues
Author: Kibukx
License: MIT License
License-File: LICENSE
Keywords: config,configuration,dotenv,env,environment,validation
Classifier: Development Status :: 3 - Alpha
Classifier: Intended Audience :: Developers
Classifier: License :: OSI Approved :: MIT License
Classifier: Programming Language :: Python :: 3
Classifier: Programming Language :: Python :: 3.11
Classifier: Programming Language :: Python :: 3.12
Classifier: Programming Language :: Python :: 3.13
Classifier: Topic :: Software Development :: Libraries :: Python Modules
Classifier: Topic :: System :: Systems Administration
Classifier: Typing :: Typed
Requires-Python: >=3.11
Requires-Dist: click>=8.1.8
Requires-Dist: python-dotenv>=1.1.1
Requires-Dist: pyyaml>=6.0.3
Requires-Dist: rich>=14.1.0
Requires-Dist: tomli-w>=1.0.0
Requires-Dist: tomli>=2.2.1
Provides-Extra: dev
Requires-Dist: bandit>=1.7.5; extra == 'dev'
Requires-Dist: black>=25.9.0; extra == 'dev'
Requires-Dist: mypy>=1.18.2; extra == 'dev'
Requires-Dist: pip-audit>=2.6.1; extra == 'dev'
Requires-Dist: pip-licenses>=4.3.0; extra == 'dev'
Requires-Dist: pre-commit>=4.3.0; extra == 'dev'
Requires-Dist: pytest-cov>=7.0.0; extra == 'dev'
Requires-Dist: pytest-xdist>=3.8.0; extra == 'dev'
Requires-Dist: pytest>=8.4.2; extra == 'dev'
Requires-Dist: ruff>=0.13.3; extra == 'dev'
Requires-Dist: safety>=2.3.5; extra == 'dev'
Requires-Dist: types-click>=7.1.8; extra == 'dev'
Requires-Dist: types-pyyaml>=6.0.12.20250915; extra == 'dev'
